graphviz_artist/__init__.py
graphviz_artist/attr.py
graphviz_artist/graph.py
graphviz_artist-0.2.1.dist-info/LICENSE
graphviz_artist-0.2.1.dist-info/METADATA
graphviz_artist-0.2.1.dist-info/WHEEL
graphviz_artist-0.2.1.dist-info/top_level.txt
graphviz_artist-0.2.1.dist-info/RECORD
