Metadata-Version: 2.1
Name: graphviz-artist
Version: 0.2.1
Summary: A chance to focus on graph drawing itself, forget APIs and other stuffs.
Home-page: https://github.com/thautwarm/graphviz-artist
Author: thautwarm
Author-email: twshere@outlook.com
License: mit
Keywords: graphviz,graph-drawing,dsl
Platform: any
Classifier: Programming Language :: Python :: 2.7
Classifier: Programming Language :: Python :: 3.4
Classifier: Programming Language :: Python :: 3.5
Classifier: Programming Language :: Python :: 3.6
Classifier: Programming Language :: Python :: 3.7
Classifier: Programming Language :: Python :: 3.8
Classifier: Programming Language :: Python :: 3.9
Classifier: Programming Language :: Python :: Implementation :: CPython
License-File: LICENSE
Requires-Dist: graphviz
Requires-Dist: typing
